LICENSE
MANIFEST.in
README.md
setup.cfg
setup.py
earningstrats/__init__.py
earningstrats/earnings.py
earningstrats/option_set.py
earningstrats/options.py
earningstrats/stock_data.py
earningstrats/today_data.py
earningstrats/util.py
earningstrats.egg-info/PKG-INFO
earningstrats.egg-info/SOURCES.txt
earningstrats.egg-info/dependency_links.txt
earningstrats.egg-info/entry_points.txt
earningstrats.egg-info/requires.txt
earningstrats.egg-info/top_level.txt
earningstrats/input_data/cboesymboldirequityindex.csv
earningstrats/input_data/cboesymboldirweeklys.csv