Metadata-Version: 2.1
Name: earningstrats
Version: 0.1.4
Summary: Use Stock Earnings Data to formulate strategies
Home-page: https://github.com/woojuyim/earningstrats
Download-URL: https://github.com/woojuyim/earningstrats/archive/refs/tags/v0.1.1.tar.gz
Author: Wooju Yim
Author-email: woojuyim126@gmail.com
License: Apache License
Keywords: pandas,yahoo finance,earnings,gamma,options
Platform: any
Classifier: License :: OSI Approved :: Apache Software License
Classifier: Development Status :: 4 - Beta
Classifier: Operating System :: OS Independent
Classifier: Intended Audience :: Developers
Classifier: Topic :: Office/Business :: Financial :: Investment
Classifier: Topic :: Scientific/Engineering :: Interface Engine/Protocol Translator
Classifier: Topic :: Software Development :: Libraries :: Python Modules
Classifier: Programming Language :: Python :: 3.9
Classifier: Programming Language :: Python :: 3.10
License-File: LICENSE
